auctm_database_connector/__init__.py
auctm_database_connector/bifrost.py
auctm_database_connector/decision_science.py
auctm_database_connector/sagemaker.py
auctm_database_connector/squadiq.py
auctm_database_connector/substrate.py
auctm_database_connector/utils.py
database_connector/__init__.py
database_connector/bifrost.py
database_connector/decision_science.py
database_connector/sagemaker.py
database_connector/squadiq.py
database_connector/substrate.py
database_connector/utils.py
squad_sagemaker_db_connector-0.2.dist-info/LICENSE
squad_sagemaker_db_connector-0.2.dist-info/METADATA
squad_sagemaker_db_connector-0.2.dist-info/WHEEL
squad_sagemaker_db_connector-0.2.dist-info/top_level.txt
squad_sagemaker_db_connector-0.2.dist-info/RECORD
