Metadata-Version: 2.1
Name: squad-sagemaker-db-connector
Version: 0.2
Summary: A pluggable connector that allows users (admins) to execute SQL, view, and export the results.
Home-page: https://github.com/squadrun/auctm-database-connector
Author: Ujjwal Gupta
Author-email: ujjwal.gupta@squadstack.com
License: MIT
Keywords: Db connector
Classifier: Development Status :: 5 - Production/Stable
Classifier: Intended Audience :: Developers
Classifier: License :: OSI Approved :: MIT License
Classifier: Topic :: Utilities
Classifier: Framework :: Django :: 1.7
Classifier: Framework :: Django :: 1.8
Classifier: Framework :: Django :: 1.9
Classifier: Programming Language :: Python :: 2
Classifier: Programming Language :: Python :: 2.7
Classifier: Programming Language :: Python :: 3
Classifier: Programming Language :: Python :: 3.4
License-File: LICENSE
Requires-Dist: boto3 (==1.14.60)
Requires-Dist: psycopg2-binary (==2.8.6)
Requires-Dist: SQLAlchemy (==1.3.19)
